daita/.env
daita/__init__.py
daita/daita.py
daita/daita_logo_console.txt
daita/dashboard.py
daita/footer.py
daita/load_env.py
daita/upload_images.py
daita/upload_zip.py
daita/utils.py
daita-0.0.8.dist-info/LICENSE
daita-0.0.8.dist-info/METADATA
daita-0.0.8.dist-info/WHEEL
daita-0.0.8.dist-info/entry_points.txt
daita-0.0.8.dist-info/top_level.txt
daita-0.0.8.dist-info/RECORD
