Metadata-Version: 2.1
Name: daita
Version: 0.0.8
Summary: DAITA's official easy-to-use Python library.
Home-page: https://github.com/daita-technologies/daita-python-library
Author: DAITA Technologies
Author-email: contact@daita.tech
License: MIT
Project-URL: Homepage, https://daita.tech
Project-URL: Web-App, https://app.daita.tech
Project-URL: GitHub, https://github.com/daita-technologies
Project-URL: Source, https://github.com/daita-technologies/daita-python-library
Classifier: Development Status :: 1 - Planning
Classifier: License :: OSI Approved :: MIT License
Classifier: Operating System :: POSIX :: Linux
Classifier: Operating System :: MacOS
Classifier: Operating System :: Microsoft :: Windows
Classifier: Programming Language :: Python :: 3
Classifier: Programming Language :: Python :: 3.8
Classifier: Programming Language :: Python :: 3.9
Requires-Python: >=3.8
License-File: LICENSE
Requires-Dist: python-dotenv
Requires-Dist: requests
Requires-Dist: tqdm
Requires-Dist: urllib3 (==1.26.2)
